malware_traffic_detection/AE_Model.py
malware_traffic_detection/__init__.py
malware_traffic_detection/main_entry.py
malware_traffic_detection/pcap2input/__init__.py
malware_traffic_detection/pcap2input/flows2features.py
malware_traffic_detection/pcap2input/pcap2flows.py
malware_traffic_detection/pcap2input/pcap2flows_by_dlls.py
malware_traffic_detection/pcap2input/pcap2flows_by_splitcap.py
malware_traffic_detection/utilities/__init__.py
malware_traffic_detection/utilities/data_preprocessing.py
malware_traffic_detection/utilities/metrics_measure.py
malware_traffic_detection/utilities/random_control.py
malware_traffic_detection/utilities/show_data.py
malware_traffic_detection-0.1.1.0.dist-info/METADATA
malware_traffic_detection-0.1.1.0.dist-info/RECORD
malware_traffic_detection-0.1.1.0.dist-info/WHEEL
malware_traffic_detection-0.1.1.0.dist-info/top_level.txt
