Metadata-Version: 2.1
Name: malware-traffic-detection
Version: 0.1.1.0
Summary: Traffic analysis by Scapy
Home-page: https://github.com/Learn-Live/malware_traffic_detection
Author: Quinn (Kun) 
Author-email: kun.bj@foxmail.com
License: MIT
Platform: UNKNOWN
Requires-Dist: Scapy (<7.0.0,>=2.4.0)
